tamarin_iac/__init__.py
tamarin_iac/tamarin.py
tamarin_iac-0.2.0.2.dist-info/LICENSE
tamarin_iac-0.2.0.2.dist-info/METADATA
tamarin_iac-0.2.0.2.dist-info/WHEEL
tamarin_iac-0.2.0.2.dist-info/entry_points.txt
tamarin_iac-0.2.0.2.dist-info/top_level.txt
tamarin_iac-0.2.0.2.dist-info/RECORD
