Metadata-Version: 2.1
Name: tamarin-iac
Version: 0.2.0.2
Summary: Infrastructure as code
Home-page: https://github.com/AlissonMMenezes/Tamarin
Author: Alisson Machado
Author-email: alisson.itops@gmail.com
License: UNKNOWN
Platform: UNKNOWN
Classifier: Programming Language :: Python :: 3
Classifier: License :: OSI Approved :: MIT License
Classifier: Operating System :: OS Independent
Requires-Python: >=3.6
License-File: LICENSE
Requires-Dist: paramiko (==2.9.2)
Requires-Dist: PyYAML (==6.0)
Requires-Dist: setuptools (==60.5.0)
Requires-Dist: terminaltables (==3.1.10)
